twitter_xyber/__init__.py
twitter_xyber/scraper - Copy (2).py
twitter_xyber/scraper - Copy.py
twitter_xyber/scraper-old.py
twitter_xyber/scraper.py
twitter_xyber-2.0.0.dist-info/METADATA
twitter_xyber-2.0.0.dist-info/WHEEL
twitter_xyber-2.0.0.dist-info/top_level.txt
twitter_xyber-2.0.0.dist-info/RECORD
